genoss/api/completions_routes.py
genoss/api/embeddings_routes.py
genoss/api/misc_routes.py
genoss/auth/auth_handler.py
genoss/commands/start_genoss_server.py
genoss/default_server.py
genoss/entities/chat/chat_completion.py
genoss/entities/chat/message.py
genoss/llm/base_genoss.py
genoss/llm/fake_llm.py
genoss/llm/hf_hub/base_hf_hub.py
genoss/llm/hf_inference_endpoint/hf_inference_endpoint.py
genoss/llm/local/base_local.py
genoss/llm/local/gpt4all.py
genoss/llm/openai_llm/openai_llm.py
genoss/prompts/prompt_template.py
genoss/services/chat_completion_registry.py
genoss/services/model_routing_helpers.py
genoss-0.0.2a3.dist-info/METADATA
genoss-0.0.2a3.dist-info/WHEEL
genoss-0.0.2a3.dist-info/entry_points.txt
genoss-0.0.2a3.dist-info/RECORD
