Metadata-Version: 2.1
Name: genoss
Version: 0.0.2a3
Summary: Replace OpenAI GPT with any LLMs in your app with one line. Common Inference API for all LLMs either Private or Public (Anthropic, Llama, GPT, Vertex, ...)
Home-page: https://genoss.ai/
Keywords: server,llm
Author: mattzcarey
Author-email: mattc@aleios.com
Requires-Python: >=3.11,<4.0
Classifier: Framework :: FastAPI
Classifier: Programming Language :: Python :: 3
Classifier: Programming Language :: Python :: 3.11
Classifier: Topic :: Scientific/Engineering :: Artificial Intelligence
Requires-Dist: click (>=8.1.7,<9.0.0)
Requires-Dist: fastapi[all] (>=0.95.1,<0.96.0)
Requires-Dist: loguru (>=0.7.0,<0.8.0)
Requires-Dist: pydantic[dotenv] (==1.10.12)
Requires-Dist: uvicorn (>=0.23.1,<0.24.0)
Project-URL: Repository, https://github.com/OpenGenerativeAI/GenossGPT
